{
  "analysis": "overnight_bonferroni_intraday_us_equity_broad",
  "basket": "us_equity_broad",
  "tickers": [
    "SPY",
    "QQQ",
    "IWM",
    "MDY"
  ],
  "bonferroni_alpha": 0.0125,
  "date_range": {
    "start": "2016-01-01",
    "end": "2026-04-01"
  },
  "param_grid": [
    0,
    -0.001,
    -0.002,
    -0.003,
    -0.005
  ],
  "n_bootstrap": 2000,
  "n_permutation": 2000,
  "fee_mode": "shared/fees.py (per-trade, price-dependent)",
  "validation": {
    "spy_threshold_0_net_sharpe": 0.832953,
    "spy_n_trades": 1176,
    "spy_avg_fee_bps": 0.931,
    "target_sharpe": 1.16,
    "match": false
  },
  "passing_tickers": [],
  "failing_tickers": [
    "SPY",
    "QQQ",
    "IWM",
    "MDY"
  ],
  "ticker_results": {
    "SPY": {
      "ticker": "SPY",
      "optimal_threshold": -0.001,
      "net_sharpe": 0.849139,
      "n_trades": 982,
      "cagr": 0.038593,
      "max_drawdown": -0.163698,
      "fees_rt_bps": 1.0,
      "avg_fee_rt_bps": 0.931,
      "gate1_ttest_p": 0.04700573,
      "gate1_pass": false,
      "gate2_boot_p5_sharpe": -0.035453,
      "gate2_pass": false,
      "gate3_permutation_p": 0.0385,
      "gate3_pass": false,
      "all_gates_pass": false,
      "bonferroni_alpha": 0.0125,
      "grid": [
        {
          "filter_threshold": 0,
          "sharpe": 0.833,
          "n_trades": 1176,
          "mean_ret_bps": 3.913,
          "hit_rate": 0.5655
        },
        {
          "filter_threshold": -0.001,
          "sharpe": 0.8491,
          "n_trades": 982,
          "mean_ret_bps": 4.265,
          "hit_rate": 0.5631
        },
        {
          "filter_threshold": -0.002,
          "sharpe": 0.6533,
          "n_trades": 818,
          "mean_ret_bps": 3.51,
          "hit_rate": 0.5538
        },
        {
          "filter_threshold": -0.003,
          "sharpe": 0.6452,
          "n_trades": 673,
          "mean_ret_bps": 3.698,
          "hit_rate": 0.5572
        },
        {
          "filter_threshold": -0.005,
          "sharpe": 0.748,
          "n_trades": 482,
          "mean_ret_bps": 4.617,
          "hit_rate": 0.5602
        }
      ]
    },
    "QQQ": {
      "ticker": "QQQ",
      "optimal_threshold": -0.001,
      "net_sharpe": 0.71283,
      "n_trades": 1034,
      "cagr": 0.038888,
      "max_drawdown": -0.177219,
      "fees_rt_bps": 1.0,
      "avg_fee_rt_bps": 1.206,
      "gate1_ttest_p": 0.07453104,
      "gate1_pass": false,
      "gate2_boot_p5_sharpe": -0.112751,
      "gate2_pass": false,
      "gate3_permutation_p": 0.0705,
      "gate3_pass": false,
      "all_gates_pass": false,
      "bonferroni_alpha": 0.0125,
      "grid": [
        {
          "filter_threshold": 0,
          "sharpe": 0.6814,
          "n_trades": 1163,
          "mean_ret_bps": 3.869,
          "hit_rate": 0.5563
        },
        {
          "filter_threshold": -0.001,
          "sharpe": 0.7128,
          "n_trades": 1034,
          "mean_ret_bps": 4.219,
          "hit_rate": 0.5629
        },
        {
          "filter_threshold": -0.002,
          "sharpe": 0.5108,
          "n_trades": 908,
          "mean_ret_bps": 3.112,
          "hit_rate": 0.5485
        },
        {
          "filter_threshold": -0.003,
          "sharpe": 0.3378,
          "n_trades": 798,
          "mean_ret_bps": 2.096,
          "hit_rate": 0.5464
        },
        {
          "filter_threshold": -0.005,
          "sharpe": 0.6052,
          "n_trades": 629,
          "mean_ret_bps": 3.857,
          "hit_rate": 0.5612
        }
      ]
    },
    "IWM": {
      "ticker": "IWM",
      "optimal_threshold": -0.003,
      "net_sharpe": 0.845905,
      "n_trades": 941,
      "cagr": 0.04449,
      "max_drawdown": -0.17005,
      "fees_rt_bps": 2.0,
      "avg_fee_rt_bps": 1.571,
      "gate1_ttest_p": 0.05123211,
      "gate1_pass": false,
      "gate2_boot_p5_sharpe": 0.040133,
      "gate2_pass": true,
      "gate3_permutation_p": 0.0545,
      "gate3_pass": false,
      "all_gates_pass": false,
      "bonferroni_alpha": 0.0125,
      "grid": [
        {
          "filter_threshold": 0,
          "sharpe": 0.8078,
          "n_trades": 1261,
          "mean_ret_bps": 4.635,
          "hit_rate": 0.5726
        },
        {
          "filter_threshold": -0.001,
          "sharpe": 0.8028,
          "n_trades": 1155,
          "mean_ret_bps": 4.709,
          "hit_rate": 0.5706
        },
        {
          "filter_threshold": -0.002,
          "sharpe": 0.8207,
          "n_trades": 1044,
          "mean_ret_bps": 4.89,
          "hit_rate": 0.5738
        },
        {
          "filter_threshold": -0.003,
          "sharpe": 0.8459,
          "n_trades": 941,
          "mean_ret_bps": 5.212,
          "hit_rate": 0.576
        },
        {
          "filter_threshold": -0.005,
          "sharpe": 0.4835,
          "n_trades": 751,
          "mean_ret_bps": 3.178,
          "hit_rate": 0.5606
        }
      ]
    },
    "MDY": {
      "ticker": "MDY",
      "optimal_threshold": -0.003,
      "net_sharpe": 0.366011,
      "n_trades": 844,
      "cagr": 0.014453,
      "max_drawdown": -0.19294,
      "fees_rt_bps": 2.0,
      "avg_fee_rt_bps": 0.83,
      "gate1_ttest_p": 0.25157436,
      "gate1_pass": false,
      "gate2_boot_p5_sharpe": -0.557213,
      "gate2_pass": false,
      "gate3_permutation_p": 0.2415,
      "gate3_pass": false,
      "all_gates_pass": false,
      "bonferroni_alpha": 0.0125,
      "grid": [
        {
          "filter_threshold": 0,
          "sharpe": 0.2919,
          "n_trades": 1208,
          "mean_ret_bps": 1.553,
          "hit_rate": 0.5488
        },
        {
          "filter_threshold": -0.001,
          "sharpe": 0.2161,
          "n_trades": 1085,
          "mean_ret_bps": 1.19,
          "hit_rate": 0.5465
        },
        {
          "filter_threshold": -0.002,
          "sharpe": 0.2342,
          "n_trades": 952,
          "mean_ret_bps": 1.344,
          "hit_rate": 0.5473
        },
        {
          "filter_threshold": -0.003,
          "sharpe": 0.366,
          "n_trades": 844,
          "mean_ret_bps": 2.192,
          "hit_rate": 0.5498
        },
        {
          "filter_threshold": -0.005,
          "sharpe": 0.145,
          "n_trades": 644,
          "mean_ret_bps": 0.915,
          "hit_rate": 0.5404
        }
      ]
    }
  }
}